git_pr_linear_merge/__init__.py
git_pr_linear_merge/auth.py
git_pr_linear_merge/cfg.py
git_pr_linear_merge/logger.py
git_pr_linear_merge/main.py
git_pr_linear_merge-1.1.1.dist-info/LICENSE
git_pr_linear_merge-1.1.1.dist-info/METADATA
git_pr_linear_merge-1.1.1.dist-info/WHEEL
git_pr_linear_merge-1.1.1.dist-info/entry_points.txt
git_pr_linear_merge-1.1.1.dist-info/top_level.txt
git_pr_linear_merge-1.1.1.dist-info/RECORD
