Metadata-Version: 2.1
Name: git-pr-linear-merge
Version: 1.1.1
Summary: A command line utility to list and merge GitHub pull requests while maintaining linear history
Home-page: https://github.com/waldobronchart/git-pr-linear-merge
Author: Waldo Bronchart
Author-email: wbronchart@gmail.com
License: MIT
Project-URL: Source, https://github.com/waldobronchart/git-pr-linear-merge
Project-URL: Bug Tracker, https://github.com/waldobronchart/git-pr-linear-merge/issues
Keywords: github,pull request,linear merge,linear history,semi-linear merge
Classifier: Programming Language :: Python :: 3
Classifier: License :: OSI Approved :: MIT License
Classifier: Operating System :: OS Independent
Classifier: Development Status :: 2 - Pre-Alpha
Classifier: Intended Audience :: Developers
Classifier: Topic :: Software Development :: Version Control :: Git
Requires-Python: >=3.6
License-File: LICENSE
Requires-Dist: GitPython (==3.1.30)
Requires-Dist: PyGithub (==1.54.1)
Requires-Dist: tabulate (==0.8.9)
Requires-Dist: requests (==2.31.0)
Requires-Dist: colorama (==0.4.4)
